_cluster_analysis.cp39-win_amd64.pyd
_cna.cp39-win_amd64.pyd
_neigh.cp39-win_amd64.pyd
_nep.cp39-win_amd64.pyd
_ptm.cp39-win_amd64.pyd
_rdf.cp39-win_amd64.pyd
_voronoi_analysis.cp39-win_amd64.pyd
mdapy/ackland_jones_analysis.py
mdapy/atomic_strain.py
mdapy/bond_analysis.py
mdapy/box.py
mdapy/cell_opt.py
mdapy/centro_symmetry_parameter.py
mdapy/cluser_analysis.py
mdapy/common_neighbor_analysis.py
mdapy/common_neighbor_parameter.py
mdapy/create_polycrystalline.py
mdapy/dft2nepxyz.py
mdapy/eam_average.py
mdapy/eam_generate.py
mdapy/entropy.py
mdapy/identify_diamond_structure.py
mdapy/identify_SFs_TBs.py
mdapy/lattice_maker.py
mdapy/lindemann_parameter.py
mdapy/load_save_data.py
mdapy/main.py
mdapy/mean_squared_displacement.py
mdapy/minimizer.py
mdapy/nearest_neighbor.py
mdapy/neighbor.py
mdapy/orthogonal_box.py
mdapy/pair_distribution.py
mdapy/perturb_model.py
mdapy/phonon.py
mdapy/pigz.py
mdapy/plotset.py
mdapy/polyhedral_template_matching.py
mdapy/potential.py
mdapy/replicate.py
mdapy/spatial_binning.py
mdapy/steinhardt_bond_orientation.py
mdapy/system.py
mdapy/temperature.py
mdapy/tool_function.py
mdapy/visualize.py
mdapy/void_distribution.py
mdapy/voronoi_analysis.py
mdapy/warren_cowley_parameter.py
mdapy/__init__.py
mdapy/__main__.py
mdapy/cluster/_cluster.cpp
mdapy/cna/_cna.cpp
mdapy/neigh/_neigh.cpp
mdapy/nep/_nep.cpp
mdapy/ptm/_ptm.cpp
mdapy/rdf/_rdf.cpp
mdapy/voronoi/_voro.cpp
mdapy-0.11.5.data/platlib/.load-order-mdapy-0.11.5
mdapy-0.11.5.data/platlib/libomp140.x86_64-d0235d7afb44efa8c15d24b598ad88be.dll
mdapy-0.11.5.data/platlib/msvcp140-6c5b9a5d8a723a71e2b740c0fa46ebd9.dll
mdapy-0.11.5.dist-info/DELVEWHEEL
mdapy-0.11.5.dist-info/entry_points.txt
mdapy-0.11.5.dist-info/LICENSE
mdapy-0.11.5.dist-info/METADATA
mdapy-0.11.5.dist-info/RECORD
mdapy-0.11.5.dist-info/top_level.txt
mdapy-0.11.5.dist-info/WHEEL
