Metadata-Version: 2.1
Name: mdapy
Version: 0.11.5
Summary: A simple, fast and cross-platform python library to handle the data generated from molecular dynamics simulations.
Home-page: https://github.com/mushroomfire/mdapy
Author: mushroomfire aka HerrWu
Author-email: mushroomfire aka HerrWu <yongchao_wu@bit.edu.cn>
License: BSD 3-Clause License for mdapy
Project-URL: Homepage, https://github.com/mushroomfire/mdapy
Project-URL: Documentation, https://mdapy.readthedocs.io/
Project-URL: Issue_Tracker, https://github.com/mushroomfire/mdapy/issues
Classifier: License :: OSI Approved :: BSD License
Classifier: Programming Language :: Python :: 3.8
Classifier: Programming Language :: Python :: 3.9
Classifier: Programming Language :: Python :: 3.10
Classifier: Programming Language :: Python :: 3.11
Classifier: Operating System :: Microsoft :: Windows
Classifier: Operating System :: POSIX :: Linux
Classifier: Operating System :: MacOS
Requires-Python: >=3.8,<3.12
License-File: LICENSE
Requires-Dist: taichi>=1.7.1
Requires-Dist: numpy<2.0
Requires-Dist: scipy
Requires-Dist: polars>=1.8.0
Requires-Dist: matplotlib
Requires-Dist: polyscope
Requires-Dist: tqdm
Provides-Extra: all
Requires-Dist: k3d; extra == "all"
Requires-Dist: pyfftw; extra == "all"
Provides-Extra: k3d
Requires-Dist: k3d; extra == "k3d"
Provides-Extra: pyfftw
Requires-Dist: pyfftw; extra == "pyfftw"
